alphasarasa/__init__.py
alphasarasa/locate.py
encontrar/__init__.py
encontrar/locate.py
sisi/__init__.py
sisi/locate.py
alphasarasa-0.0.0.dist-info/METADATA
alphasarasa-0.0.0.dist-info/WHEEL
alphasarasa-0.0.0.dist-info/top_level.txt
alphasarasa-0.0.0.dist-info/RECORD
